wide2narrow/wide2narrow.sv
module wide2narrow(
    input clk_wide,
    input clk_narrow,
    //input rst_wide_n,
    input rst_narrow_n,
    input [15:0] data_wide,
    output reg [7:0] data_narrow
);

      always @(posedge clk_narrow or negedge rst_narrow_n)
      begin
          if (!rst_narrow_n) begin
              data_narrow <= 8'b0;
          end else begin
              if (clk_wide) begin
                  data_narrow <= data_wide[7:0];
              end else begin
                  data_narrow <= data_wide[15:8];
              end
          end
      end
endmodule

wide2narrow/trace.vcd
$version Generated by VerilatedVcd $end
$date Sun Aug  7 22:02:24 2022
 $end
$timescale   1ps $end

 $scope module TOP $end
  $var wire  1 $ clk_narrow $end
  $var wire  1 # clk_wide $end
  $var wire  8 ' data_narrow [7:0] $end
  $var wire 16 & data_wide [15:0] $end
  $var wire  1 % rst_narrow_n $end
  $scope module wide2narrow $end
   $var wire  1 $ clk_narrow $end
   $var wire  1 # clk_wide $end
   $var wire  8 ' data_narrow [7:0] $end
   $var wire 16 & data_wide [15:0] $end
   $var wire  1 % rst_narrow_n $end
  $upscope $end
 $upscope $end
$enddefinitions $end


#5
1#
1$
1%
b0000000010101101 &
b10101101 '
#15
#25
#35
#45
0$
#55
#65
#75
#85
0#
1$
b0000000010110000 &
b00000000 '
#95
#105
#115
#125
0$
#135
#145
#155
#165
1#
1$
b0000000010110011 &
b10110011 '
#175
#185
#195
#205
0$
#215
#225
#235
#245
0#
1$
b0000000010110110 &
b00000000 '
#255
#265
#275
#285
0$
#295
#305
#315
#325
1#
1$
b0000000010111001 &
b10111001 '
#335
#345
#355
#365
0$
#375
#385
#395
#405
0#
1$
b0000000010111100 &
b00000000 '
#415
#425
#435
#445
0$
#455
#465
#475
#485
1#
1$
b0000000010111111 &
b10111111 '
#495
#505
#515
#525
0$
#535
#545
#555
#565
0#
1$
b0000000011000010 &
b00000000 '
#575
#585
#595
#605
0$
#615
#625
#635
#645
1#
1$
b0000000011000101 &
b11000101 '
#655
#665
#675
#685
0$
#695
#705
#715
#725
0#
1$
b0000000011001000 &
b00000000 '
#735
#745
#755
#765
0$
#775
#785
#795
#805
1#
1$
b0000000011001011 &
b11001011 '
#815
#825
#835
#845
0$
#855
#865
#875
#885
0#
1$
b0000000011001110 &
b00000000 '
#895
#905
#915
#925
0$
#935
#945
#955
#965
1#
1$
b0000000011010001 &
b11010001 '
#975
#985
#995
#1005
0$
#1015
#1025
#1035
#1045
0#
1$
b0000000011010100 &
b00000000 '
#1055
#1065
#1075
#1085
0$
#1095
#1105
#1115
#1125
1#
1$
b0000000011010111 &
b11010111 '
#1135
#1145
#1155
#1165
0$
#1175
#1185
#1195
#1205
0#
1$
b0000000011011010 &
b00000000 '
#1215
#1225
#1235
#1245
0$
#1255
#1265
#1275
#1285
1#
1$
b0000000011011101 &
b11011101 '
#1295
#1305
#1315
#1325
0$
#1335
#1345
#1355
#1365
0#
1$
b0000000011100000 &
b00000000 '
#1375
#1385
#1395
#1405
0$
#1415
#1425
#1435
#1445
1#
1$
b0000000011100011 &
b11100011 '
#1455
#1465
#1475
#1485
0$
#1495
#1505
#1515
#1525
0#
1$
b0000000011100110 &
b00000000 '
#1535
#1545
#1555
#1565
0$
#1575
#1585
#1595
#1605
1#
1$
b0000000011101001 &
b11101001 '
#1615
#1625
#1635
#1645
0$
#1655
#1665
#1675
#1685
0#
1$
b0000000011101100 &
b00000000 '
#1695
#1705
#1715
#1725
0$
#1735
#1745
#1755
#1765
1#
1$
b0000000011101111 &
b11101111 '
#1775
#1785
#1795
#1805
0$
#1815
#1825
#1835
#1845
0#
1$
b0000000011110010 &
b00000000 '
#1855
#1865
#1875
#1885
0$
#1895
#1905
#1915
#1925
1#
1$
b0000000011110101 &
b11110101 '
#1935
#1945
#1955
#1965
0$
#1975
#1985
#1995
#2005
0#
1$
b0000000011111000 &
b00000000 '
#2015
#2025
#2035
#2045
0$
#2055
#2065
#2075
#2085
1#
1$
b0000000011111011 &
b11111011 '
#2095
#2105
#2115
#2125
0$
#2135
#2145
#2155
#2165
0#
1$
b0000000011111110 &
b00000000 '
#2175
#2185
#2195
#2205
0$
#2215
#2225
#2235
#2245
1#
1$
b0000000100000001 &
b00000001 '
#2255
#2265
#2275
#2285
0$
#2295
#2305
#2315
#2325
0#
1$
b0000000100000100 &
#2335
#2345
#2355
#2365
0$
#2375
#2385
#2395
#2405
1#
1$
b0000000100000111 &
b00000111 '
#2415
#2425
#2435
#2445
0$
#2455
#2465
#2475
#2485
0#
1$
b0000000100001010 &
b00000001 '
#2495
#2505
#2515
#2525
0$
#2535
#2545
#2555
#2565
1#
1$
b0000000100001101 &
b00001101 '
#2575
#2585
#2595
#2605
0$
#2615
#2625
#2635
#2645
0#
1$
b0000000100010000 &
b00000001 '
#2655
#2665
#2675
#2685
0$
#2695
#2705
#2715
#2725
1#
1$
b0000000100010011 &
b00010011 '
#2735
#2745
#2755
#2765
0$
#2775
#2785
#2795
#2805
0#
1$
b0000000100010110 &
b00000001 '
#2815
#2825
#2835
#2845
0$
#2855
#2865
#2875
#2885
1#
1$
b0000000100011001 &
b00011001 '
#2895
#2905
#2915
#2925
0$
#2935
#2945
#2955
#2965
0#
1$
b0000000100011100 &
b00000001 '
#2975
#2985
#2995
#3005
0$
#3015
#3025
#3035
#3045
1#
1$
b0000000100011111 &
b00011111 '
#3055
#3065
#3075
#3085
0$
#3095
#3105
#3115
#3125
0#
1$
b0000000100100010 &
b00000001 '
#3135
#3145
#3155
#3165
0$
#3175
#3185
#3195
#3205
1#
1$
b0000000100100101 &
b00100101 '
#3215
#3225
#3235
#3245
0$
#3255
#3265
#3275
#3285
0#
1$
b0000000100101000 &
b00000001 '
#3295
#3305
#3315
#3325
0$
#3335
#3345
#3355
#3365
1#
1$
b0000000100101011 &
b00101011 '
#3375
#3385
#3395
#3405
0$
#3415
#3425
#3435
#3445
0#
1$
b0000000100101110 &
b00000001 '
#3455
#3465
#3475
#3485
0$
#3495
#3505
#3515
#3525
1#
1$
b0000000100110001 &
b00110001 '
#3535
#3545
#3555
#3565
0$
#3575
#3585
#3595
#3605
0#
1$
b0000000100110100 &
b00000001 '
#3615
#3625
#3635
#3645
0$
#3655
#3665
#3675
#3685
1#
1$
b0000000100110111 &
b00110111 '
#3695
#3705
#3715
#3725
0$
#3735
#3745
#3755
#3765
0#
1$
b0000000100111010 &
b00000001 '
#3775
#3785
#3795
#3805
0$
#3815
#3825
#3835
#3845
1#
1$
b0000000100111101 &
b00111101 '
#3855
#3865
#3875
#3885
0$
#3895
#3905
#3915
#3925
0#
1$
b0000000101000000 &
b00000001 '
#3935
#3945
#3955
#3965
0$
#3975
#3985
#3995
#4005
1#
1$
b0000000101000011 &
b01000011 '
#4015
#4025
#4035
#4045
0$
#4055
#4065
#4075
#4085
0#
1$
b0000000101000110 &
b00000001 '
#4095
#4105
#4115
#4125
0$
#4135
#4145
#4155
#4165
1#
1$
b0000000101001001 &
b01001001 '
#4175
#4185
#4195
#4205
0$
#4215
#4225
#4235
#4245
0#
1$
b0000000101001100 &
b00000001 '
#4255
#4265
#4275
#4285
0$
#4295
#4305
#4315
#4325
1#
1$
b0000000101001111 &
b01001111 '
#4335
#4345
#4355
#4365
0$
#4375
#4385
#4395
#4405
0#
1$
b0000000101010010 &
b00000001 '
#4415
#4425
#4435
#4445
0$
#4455
#4465
#4475
#4485
1#
1$
b0000000101010101 &
b01010101 '
#4495
#4505
#4515
#4525
0$
#4535
#4545
#4555
#4565
0#
1$
b0000000101011000 &
b00000001 '
#4575
#4585
#4595
#4605
0$
#4615
#4625
#4635
#4645
1#
1$
b0000000101011011 &
b01011011 '
#4655
#4665
#4675
#4685
0$
#4695
#4705
#4715
#4725
0#
1$
b0000000101011110 &
b00000001 '
#4735
#4745
#4755
#4765
0$
#4775
#4785
#4795
#4805
1#
1$
b0000000101100001 &
b01100001 '
#4815
#4825
#4835
#4845
0$
#4855
#4865
#4875
#4885
0#
1$
b0000000101100100 &
b00000001 '
#4895
#4905
#4915
#4925
0$
#4935
#4945
#4955
#4965
1#
1$
b0000000101100111 &
b01100111 '
