divide_5/divide_5.v
module divide_5(input clk,
	            output clk_out);
    
    wire d2,d1,d0;
    reg q2,q1,q0,q2temp;

    initial begin
        q2 = 0;
        q1 = 0;
        q0 = 0;	
    end

    assign q2bar = ~q2;
    assign q1bar = ~q1;
    assign q0bar = ~q0;


    assign d0 = q2bar & q0bar;
    assign d1 = (q1&q0bar) | (q1bar & q0);
    assign d2 = q1 & q0;

    //q0
    always @(posedge clk) begin
        q0 <= d0;        	
        q1 <= d1;
        q2 <= d2;
    end
    
    always @(negedge clk) begin
    	q2temp <= q1;
    end

    assign clk_out = q1 | q2temp;

endmodule

divide_5/divide_5_tb.v
module test;

  /* Make a reset that pulses once. */
  reg reset = 0;
  initial begin
     $dumpfile("test.vcd");
     $dumpvars(0,test);

     # 17 reset = 1;
     # 11 reset = 0;
     # 29 reset = 1;
     # 5  reset =0;
     # 513 $finish;
  end

  /* Make a regular pulsing clock. */
  reg clk = 0;
  always #1 clk = !clk;

  wire clk_out;
  divide_5 c1 (.clk(clk), 
               .clk_out(clk_out));

  initial
     $monitor("At time %t, value = %h (%0d)",
              $time, clk_out, clk_out);
endmodule // test

divide_5/test.vcd
$date
	Sat Oct 21 09:15:18 2017
$end
$version
	Icarus Verilog
$end
$timescale
	1s
$end
$scope module test $end
$var wire 1 ! clk_out $end
$var reg 1 " clk $end
$var reg 1 # reset $end
$scope module c1 $end
$var wire 1 " clk $end
$var wire 1 ! clk_out $end
$var wire 1 $ d0 $end
$var wire 1 % d1 $end
$var wire 1 & d2 $end
$var wire 1 ' q0bar $end
$var wire 1 ( q1bar $end
$var wire 1 ) q2bar $end
$var reg 1 * q0 $end
$var reg 1 + q1 $end
$var reg 1 , q2 $end
$var reg 1 - q2temp $end
$upscope $end
$upscope $end
$enddefinitions $end
#0
$dumpvars
0-
0,
0+
0*
1)
1(
1'
0&
0%
1$
0#
0"
0!
$end
#1
1%
0$
0'
1*
1"
#2
0"
#3
1$
1!
0(
1'
1+
0*
1"
#4
1-
0"
#5
0%
0$
1&
0'
1*
1"
#6
0"
#7
0)
1(
0&
1'
1,
0+
0*
1"
#8
0!
0-
0"
#9
1$
1)
0,
1"
#10
0"
#11
1%
0$
0'
1*
1"
#12
0"
#13
1$
1!
0(
1'
1+
0*
1"
#14
1-
0"
#15
0%
0$
1&
0'
1*
1"
#16
0"
#17
0)
1(
0&
1'
1,
0+
0*
1"
1#
#18
0!
0-
0"
#19
1$
1)
0,
1"
#20
0"
#21
1%
0$
0'
1*
1"
#22
0"
#23
1$
1!
0(
1'
1+
0*
1"
#24
1-
0"
#25
0%
0$
1&
0'
1*
1"
#26
0"
#27
0)
1(
0&
1'
1,
0+
0*
1"
#28
0!
0-
0"
0#
#29
1$
1)
0,
1"
#30
0"
#31
1%
0$
0'
1*
1"
#32
0"
#33
1$
1!
0(
1'
1+
0*
1"
#34
1-
0"
#35
0%
0$
1&
0'
1*
1"
#36
0"
#37
0)
1(
0&
1'
1,
0+
0*
1"
#38
0!
0-
0"
#39
1$
1)
0,
1"
#40
0"
#41
1%
0$
0'
1*
1"
#42
0"
#43
1$
1!
0(
1'
1+
0*
1"
#44
1-
0"
#45
0%
0$
1&
0'
1*
1"
#46
0"
#47
0)
1(
0&
1'
1,
0+
0*
1"
#48
0!
0-
0"
#49
1$
1)
0,
1"
#50
0"
#51
1%
0$
0'
1*
1"
#52
0"
#53
1$
1!
0(
1'
1+
0*
1"
#54
1-
0"
#55
0%
0$
1&
0'
1*
1"
#56
0"
#57
0)
1(
0&
1'
1,
0+
0*
1"
1#
#58
0!
0-
0"
#59
1$
1)
0,
1"
#60
0"
#61
1%
0$
0'
1*
1"
#62
0"
0#
#63
1$
1!
0(
1'
1+
0*
1"
#64
1-
0"
#65
0%
0$
1&
0'
1*
1"
#66
0"
#67
0)
1(
0&
1'
1,
0+
0*
1"
#68
0!
0-
0"
#69
1$
1)
0,
1"
#70
0"
#71
1%
0$
0'
1*
1"
#72
0"
#73
1$
1!
0(
1'
1+
0*
1"
#74
1-
0"
#75
0%
0$
1&
0'
1*
1"
#76
0"
#77
0)
1(
0&
1'
1,
0+
0*
1"
#78
0!
0-
0"
#79
1$
1)
0,
1"
#80
0"
#81
1%
0$
0'
1*
1"
#82
0"
#83
1$
1!
0(
1'
1+
0*
1"
#84
1-
0"
#85
0%
0$
1&
0'
1*
1"
#86
0"
#87
0)
1(
0&
1'
1,
0+
0*
1"
#88
0!
0-
0"
#89
1$
1)
0,
1"
#90
0"
#91
1%
0$
0'
1*
1"
#92
0"
#93
1$
1!
0(
1'
1+
0*
1"
#94
1-
0"
#95
0%
0$
1&
0'
1*
1"
#96
0"
#97
0)
1(
0&
1'
1,
0+
0*
1"
#98
0!
0-
0"
#99
1$
1)
0,
1"
#100
0"
#101
1%
0$
0'
1*
1"
#102
0"
#103
1$
1!
0(
1'
1+
0*
1"
#104
1-
0"
#105
0%
0$
1&
0'
1*
1"
#106
0"
#107
0)
1(
0&
1'
1,
0+
0*
1"
#108
0!
0-
0"
#109
1$
1)
0,
1"
#110
0"
#111
1%
0$
0'
1*
1"
#112
0"
#113
1$
1!
0(
1'
1+
0*
1"
#114
1-
0"
#115
0%
0$
1&
0'
1*
1"
#116
0"
#117
0)
1(
0&
1'
1,
0+
0*
1"
#118
0!
0-
0"
#119
1$
1)
0,
1"
#120
0"
#121
1%
0$
0'
1*
1"
#122
0"
#123
1$
1!
0(
1'
1+
0*
1"
#124
1-
0"
#125
0%
0$
1&
0'
1*
1"
#126
0"
#127
0)
1(
0&
1'
1,
0+
0*
1"
#128
0!
0-
0"
#129
1$
1)
0,
1"
#130
0"
#131
1%
0$
0'
1*
1"
#132
0"
#133
1$
1!
0(
1'
1+
0*
1"
#134
1-
0"
#135
0%
0$
1&
0'
1*
1"
#136
0"
#137
0)
1(
0&
1'
1,
0+
0*
1"
#138
0!
0-
0"
#139
1$
1)
0,
1"
#140
0"
#141
1%
0$
0'
1*
1"
#142
0"
#143
1$
1!
0(
1'
1+
0*
1"
#144
1-
0"
#145
0%
0$
1&
0'
1*
1"
#146
0"
#147
0)
1(
0&
1'
1,
0+
0*
1"
#148
0!
0-
0"
#149
1$
1)
0,
1"
#150
0"
#151
1%
0$
0'
1*
1"
#152
0"
#153
1$
1!
0(
1'
1+
0*
1"
#154
1-
0"
#155
0%
0$
1&
0'
1*
1"
#156
0"
#157
0)
1(
0&
1'
1,
0+
0*
1"
#158
0!
0-
0"
#159
1$
1)
0,
1"
#160
0"
#161
1%
0$
0'
1*
1"
#162
0"
#163
1$
1!
0(
1'
1+
0*
1"
#164
1-
0"
#165
0%
0$
1&
0'
1*
1"
#166
0"
#167
0)
1(
0&
1'
1,
0+
0*
1"
#168
0!
0-
0"
#169
1$
1)
0,
1"
#170
0"
#171
1%
0$
0'
1*
1"
#172
0"
#173
1$
1!
0(
1'
1+
0*
1"
#174
1-
0"
#175
0%
0$
1&
0'
1*
1"
#176
0"
#177
0)
1(
0&
1'
1,
0+
0*
1"
#178
0!
0-
0"
#179
1$
1)
0,
1"
#180
0"
#181
1%
0$
0'
1*
1"
#182
0"
#183
1$
1!
0(
1'
1+
0*
1"
#184
1-
0"
#185
0%
0$
1&
0'
1*
1"
#186
0"
#187
0)
1(
0&
1'
1,
0+
0*
1"
#188
0!
0-
0"
#189
1$
1)
0,
1"
#190
0"
#191
1%
0$
0'
1*
1"
#192
0"
#193
1$
1!
0(
1'
1+
0*
1"
#194
1-
0"
#195
0%
0$
1&
0'
1*
1"
#196
0"
#197
0)
1(
0&
1'
1,
0+
0*
1"
#198
0!
0-
0"
#199
1$
1)
0,
1"
#200
0"
#201
1%
0$
0'
1*
1"
#202
0"
#203
1$
1!
0(
1'
1+
0*
1"
#204
1-
0"
#205
0%
0$
1&
0'
1*
1"
#206
0"
#207
0)
1(
0&
1'
1,
0+
0*
1"
#208
0!
0-
0"
#209
1$
1)
0,
1"
#210
0"
#211
1%
0$
0'
1*
1"
#212
0"
#213
1$
1!
0(
1'
1+
0*
1"
#214
1-
0"
#215
0%
0$
1&
0'
1*
1"
#216
0"
#217
0)
1(
0&
1'
1,
0+
0*
1"
#218
0!
0-
0"
#219
1$
1)
0,
1"
#220
0"
#221
1%
0$
0'
1*
1"
#222
0"
#223
1$
1!
0(
1'
1+
0*
1"
#224
1-
0"
#225
0%
0$
1&
0'
1*
1"
#226
0"
#227
0)
1(
0&
1'
1,
0+
0*
1"
#228
0!
0-
0"
#229
1$
1)
0,
1"
#230
0"
#231
1%
0$
0'
1*
1"
#232
0"
#233
1$
1!
0(
1'
1+
0*
1"
#234
1-
0"
#235
0%
0$
1&
0'
1*
1"
#236
0"
#237
0)
1(
0&
1'
1,
0+
0*
1"
#238
0!
0-
0"
#239
1$
1)
0,
1"
#240
0"
#241
1%
0$
0'
1*
1"
#242
0"
#243
1$
1!
0(
1'
1+
0*
1"
#244
1-
0"
#245
0%
0$
1&
0'
1*
1"
#246
0"
#247
0)
1(
0&
1'
1,
0+
0*
1"
#248
0!
0-
0"
#249
1$
1)
0,
1"
#250
0"
#251
1%
0$
0'
1*
1"
#252
0"
#253
1$
1!
0(
1'
1+
0*
1"
#254
1-
0"
#255
0%
0$
1&
0'
1*
1"
#256
0"
#257
0)
1(
0&
1'
1,
0+
0*
1"
#258
0!
0-
0"
#259
1$
1)
0,
1"
#260
0"
#261
1%
0$
0'
1*
1"
#262
0"
#263
1$
1!
0(
1'
1+
0*
1"
#264
1-
0"
#265
0%
0$
1&
0'
1*
1"
#266
0"
#267
0)
1(
0&
1'
1,
0+
0*
1"
#268
0!
0-
0"
#269
1$
1)
0,
1"
#270
0"
#271
1%
0$
0'
1*
1"
#272
0"
#273
1$
1!
0(
1'
1+
0*
1"
#274
1-
0"
#275
0%
0$
1&
0'
1*
1"
#276
0"
#277
0)
1(
0&
1'
1,
0+
0*
1"
#278
0!
0-
0"
#279
1$
1)
0,
1"
#280
0"
#281
1%
0$
0'
1*
1"
#282
0"
#283
1$
1!
0(
1'
1+
0*
1"
#284
1-
0"
#285
0%
0$
1&
0'
1*
1"
#286
0"
#287
0)
1(
0&
1'
1,
0+
0*
1"
#288
0!
0-
0"
#289
1$
1)
0,
1"
#290
0"
#291
1%
0$
0'
1*
1"
#292
0"
#293
1$
1!
0(
1'
1+
0*
1"
#294
1-
0"
#295
0%
0$
1&
0'
1*
1"
#296
0"
#297
0)
1(
0&
1'
1,
0+
0*
1"
#298
0!
0-
0"
#299
1$
1)
0,
1"
#300
0"
#301
1%
0$
0'
1*
1"
#302
0"
#303
1$
1!
0(
1'
1+
0*
1"
#304
1-
0"
#305
0%
0$
1&
0'
1*
1"
#306
0"
#307
0)
1(
0&
1'
1,
0+
0*
1"
#308
0!
0-
0"
#309
1$
1)
0,
1"
#310
0"
#311
1%
0$
0'
1*
1"
#312
0"
#313
1$
1!
0(
1'
1+
0*
1"
#314
1-
0"
#315
0%
0$
1&
0'
1*
1"
#316
0"
#317
0)
1(
0&
1'
1,
0+
0*
1"
#318
0!
0-
0"
#319
1$
1)
0,
1"
#320
0"
#321
1%
0$
0'
1*
1"
#322
0"
#323
1$
1!
0(
1'
1+
0*
1"
#324
1-
0"
#325
0%
0$
1&
0'
1*
1"
#326
0"
#327
0)
1(
0&
1'
1,
0+
0*
1"
#328
0!
0-
0"
#329
1$
1)
0,
1"
#330
0"
#331
1%
0$
0'
1*
1"
#332
0"
#333
1$
1!
0(
1'
1+
0*
1"
#334
1-
0"
#335
0%
0$
1&
0'
1*
1"
#336
0"
#337
0)
1(
0&
1'
1,
0+
0*
1"
#338
0!
0-
0"
#339
1$
1)
0,
1"
#340
0"
#341
1%
0$
0'
1*
1"
#342
0"
#343
1$
1!
0(
1'
1+
0*
1"
#344
1-
0"
#345
0%
0$
1&
0'
1*
1"
#346
0"
#347
0)
1(
0&
1'
1,
0+
0*
1"
#348
0!
0-
0"
#349
1$
1)
0,
1"
#350
0"
#351
1%
0$
0'
1*
1"
#352
0"
#353
1$
1!
0(
1'
1+
0*
1"
#354
1-
0"
#355
0%
0$
1&
0'
1*
1"
#356
0"
#357
0)
1(
0&
1'
1,
0+
0*
1"
#358
0!
0-
0"
#359
1$
1)
0,
1"
#360
0"
#361
1%
0$
0'
1*
1"
#362
0"
#363
1$
1!
0(
1'
1+
0*
1"
#364
1-
0"
#365
0%
0$
1&
0'
1*
1"
#366
0"
#367
0)
1(
0&
1'
1,
0+
0*
1"
#368
0!
0-
0"
#369
1$
1)
0,
1"
#370
0"
#371
1%
0$
0'
1*
1"
#372
0"
#373
1$
1!
0(
1'
1+
0*
1"
#374
1-
0"
#375
0%
0$
1&
0'
1*
1"
#376
0"
#377
0)
1(
0&
1'
1,
0+
0*
1"
#378
0!
0-
0"
#379
1$
1)
0,
1"
#380
0"
#381
1%
0$
0'
1*
1"
#382
0"
#383
1$
1!
0(
1'
1+
0*
1"
#384
1-
0"
#385
0%
0$
1&
0'
1*
1"
#386
0"
#387
0)
1(
0&
1'
1,
0+
0*
1"
#388
0!
0-
0"
#389
1$
1)
0,
1"
#390
0"
#391
1%
0$
0'
1*
1"
#392
0"
#393
1$
1!
0(
1'
1+
0*
1"
#394
1-
0"
#395
0%
0$
1&
0'
1*
1"
#396
0"
#397
0)
1(
0&
1'
1,
0+
0*
1"
#398
0!
0-
0"
#399
1$
1)
0,
1"
#400
0"
#401
1%
0$
0'
1*
1"
#402
0"
#403
1$
1!
0(
1'
1+
0*
1"
#404
1-
0"
#405
0%
0$
1&
0'
1*
1"
#406
0"
#407
0)
1(
0&
1'
1,
0+
0*
1"
#408
0!
0-
0"
#409
1$
1)
0,
1"
#410
0"
#411
1%
0$
0'
1*
1"
#412
0"
#413
1$
1!
0(
1'
1+
0*
1"
#414
1-
0"
#415
0%
0$
1&
0'
1*
1"
#416
0"
#417
0)
1(
0&
1'
1,
0+
0*
1"
#418
0!
0-
0"
#419
1$
1)
0,
1"
#420
0"
#421
1%
0$
0'
1*
1"
#422
0"
#423
1$
1!
0(
1'
1+
0*
1"
#424
1-
0"
#425
0%
0$
1&
0'
1*
1"
#426
0"
#427
0)
1(
0&
1'
1,
0+
0*
1"
#428
0!
0-
0"
#429
1$
1)
0,
1"
#430
0"
#431
1%
0$
0'
1*
1"
#432
0"
#433
1$
1!
0(
1'
1+
0*
1"
#434
1-
0"
#435
0%
0$
1&
0'
1*
1"
#436
0"
#437
0)
1(
0&
1'
1,
0+
0*
1"
#438
0!
0-
0"
#439
1$
1)
0,
1"
#440
0"
#441
1%
0$
0'
1*
1"
#442
0"
#443
1$
1!
0(
1'
1+
0*
1"
#444
1-
0"
#445
0%
0$
1&
0'
1*
1"
#446
0"
#447
0)
1(
0&
1'
1,
0+
0*
1"
#448
0!
0-
0"
#449
1$
1)
0,
1"
#450
0"
#451
1%
0$
0'
1*
1"
#452
0"
#453
1$
1!
0(
1'
1+
0*
1"
#454
1-
0"
#455
0%
0$
1&
0'
1*
1"
#456
0"
#457
0)
1(
0&
1'
1,
0+
0*
1"
#458
0!
0-
0"
#459
1$
1)
0,
1"
#460
0"
#461
1%
0$
0'
1*
1"
#462
0"
#463
1$
1!
0(
1'
1+
0*
1"
#464
1-
0"
#465
0%
0$
1&
0'
1*
1"
#466
0"
#467
0)
1(
0&
1'
1,
0+
0*
1"
#468
0!
0-
0"
#469
1$
1)
0,
1"
#470
0"
#471
1%
0$
0'
1*
1"
#472
0"
#473
1$
1!
0(
1'
1+
0*
1"
#474
1-
0"
#475
0%
0$
1&
0'
1*
1"
#476
0"
#477
0)
1(
0&
1'
1,
0+
0*
1"
#478
0!
0-
0"
#479
1$
1)
0,
1"
#480
0"
#481
1%
0$
0'
1*
1"
#482
0"
#483
1$
1!
0(
1'
1+
0*
1"
#484
1-
0"
#485
0%
0$
1&
0'
1*
1"
#486
0"
#487
0)
1(
0&
1'
1,
0+
0*
1"
#488
0!
0-
0"
#489
1$
1)
0,
1"
#490
0"
#491
1%
0$
0'
1*
1"
#492
0"
#493
1$
1!
0(
1'
1+
0*
1"
#494
1-
0"
#495
0%
0$
1&
0'
1*
1"
#496
0"
#497
0)
1(
0&
1'
1,
0+
0*
1"
#498
0!
0-
0"
#499
1$
1)
0,
1"
#500
0"
#501
1%
0$
0'
1*
1"
#502
0"
#503
1$
1!
0(
1'
1+
0*
1"
#504
1-
0"
#505
0%
0$
1&
0'
1*
1"
#506
0"
#507
0)
1(
0&
1'
1,
0+
0*
1"
#508
0!
0-
0"
#509
1$
1)
0,
1"
#510
0"
#511
1%
0$
0'
1*
1"
#512
0"
#513
1$
1!
0(
1'
1+
0*
1"
#514
1-
0"
#515
0%
0$
1&
0'
1*
1"
#516
0"
#517
0)
1(
0&
1'
1,
0+
0*
1"
#518
0!
0-
0"
#519
1$
1)
0,
1"
#520
0"
#521
1%
0$
0'
1*
1"
#522
0"
#523
1$
1!
0(
1'
1+
0*
1"
#524
1-
0"
#525
0%
0$
1&
0'
1*
1"
#526
0"
#527
0)
1(
0&
1'
1,
0+
0*
1"
#528
0!
0-
0"
#529
1$
1)
0,
1"
#530
0"
#531
1%
0$
0'
1*
1"
#532
0"
#533
1$
1!
0(
1'
1+
0*
1"
#534
1-
0"
#535
0%
0$
1&
0'
1*
1"
#536
0"
#537
0)
1(
0&
1'
1,
0+
0*
1"
#538
0!
0-
0"
#539
1$
1)
0,
1"
#540
0"
#541
1%
0$
0'
1*
1"
#542
0"
#543
1$
1!
0(
1'
1+
0*
1"
#544
1-
0"
#545
0%
0$
1&
0'
1*
1"
#546
0"
#547
0)
1(
0&
1'
1,
0+
0*
1"
#548
0!
0-
0"
#549
1$
1)
0,
1"
#550
0"
#551
1%
0$
0'
1*
1"
#552
0"
#553
1$
1!
0(
1'
1+
0*
1"
#554
1-
0"
#555
0%
0$
1&
0'
1*
1"
#556
0"
#557
0)
1(
0&
1'
1,
0+
0*
1"
#558
0!
0-
0"
#559
1$
1)
0,
1"
#560
0"
#561
1%
0$
0'
1*
1"
#562
0"
#563
1$
1!
0(
1'
1+
0*
1"
#564
1-
0"
#565
0%
0$
1&
0'
1*
1"
#566
0"
#567
0)
1(
0&
1'
1,
0+
0*
1"
#568
0!
0-
0"
#569
1$
1)
0,
1"
#570
0"
#571
1%
0$
0'
1*
1"
#572
0"
#573
1$
1!
0(
1'
1+
0*
1"
#574
1-
0"
#575
0%
0$
1&
0'
1*
1"
