divide_5/divide_5.v
module divide_5(input clk,
	            output clk_out);

    wire d2,d1,d0;
    reg q2,q1,q0,q2temp;
		wire q2bar, q1bar, q0bar;

    initial begin
        q2 = 0;
        q1 = 0;
        q0 = 0;
    end

    assign q2bar = ~q2;
    assign q1bar = ~q1;
    assign q0bar = ~q0;


    assign d0 = q2bar & q0bar;
    assign d1 = (q1&q0bar) | (q1bar & q0);
    assign d2 = q1 & q0;

    //q0
    always @(posedge clk) begin
        q0 <= d0;
        q1 <= d1;
        q2 <= d2;
    end

    always @(negedge clk) begin
    	q2temp <= q1;
    end

    assign clk_out = q1 | q2temp;

endmodule

divide_5/trace.vcd
$version Generated by VerilatedVcd $end
$date Sat Sep 24 16:33:31 2022
 $end
$timescale   1ns $end

 $scope module TOP $end
  $var wire  1 , clk $end
  $var wire  1 - clk_out $end
  $scope module divide_5 $end
   $var wire  1 , clk $end
   $var wire  1 - clk_out $end
   $var wire  1 % d0 $end
   $var wire  1 $ d1 $end
   $var wire  1 # d2 $end
   $var wire  1 ( q0 $end
   $var wire  1 + q0bar $end
   $var wire  1 ' q1 $end
   $var wire  1 * q1bar $end
   $var wire  1 & q2 $end
   $var wire  1 ) q2bar $end
   $var wire  1 . q2temp $end
  $upscope $end
 $upscope $end
$enddefinitions $end


#0
0#
1$
0%
0&
0'
1(
1)
1*
0+
1,
0-
0.
#10
0,
#20
1%
1'
0(
0*
1+
1,
1-
#30
0,
1.
#40
1#
0$
0%
1(
0+
1,
#50
0,
#60
0#
1&
0'
0(
0)
1*
1+
1,
#70
0,
0-
0.
#80
1%
0&
1)
1,
#90
0,
#100
1$
0%
1(
0+
1,
#110
0,
#120
1%
1'
0(
0*
1+
1,
1-
#130
0,
1.
#140
1#
0$
0%
1(
0+
1,
#150
0,
#160
0#
1&
0'
0(
0)
1*
1+
1,
#170
0,
0-
0.
#180
1%
0&
1)
1,
#190
0,
#200
1$
0%
1(
0+
1,
#210
0,
#220
1%
1'
0(
0*
1+
1,
1-
#230
0,
1.
#240
1#
0$
0%
1(
0+
1,
#250
0,
#260
0#
1&
0'
0(
0)
1*
1+
1,
#270
0,
0-
0.
#280
1%
0&
1)
1,
#290
0,
#300
1$
0%
1(
0+
1,
#310
0,
#320
1%
1'
0(
0*
1+
1,
1-
#330
0,
1.
#340
1#
0$
0%
1(
0+
1,
#350
0,
#360
0#
1&
0'
0(
0)
1*
1+
1,
#370
0,
0-
0.
#380
1%
0&
1)
1,
#390
0,
#400
1$
0%
1(
0+
1,
#410
0,
#420
1%
1'
0(
0*
1+
1,
1-
#430
0,
1.
#440
1#
0$
0%
1(
0+
1,
#450
0,
#460
0#
1&
0'
0(
0)
1*
1+
1,
#470
0,
0-
0.
#480
1%
0&
1)
1,
#490
0,
#500
1$
0%
1(
0+
1,
#510
0,
#520
1%
1'
0(
0*
1+
1,
1-
#530
0,
1.
#540
1#
0$
0%
1(
0+
1,
#550
0,
#560
0#
1&
0'
0(
0)
1*
1+
1,
#570
0,
0-
0.
#580
1%
0&
1)
1,
#590
0,
#600
1$
0%
1(
0+
1,
#610
0,
#620
1%
1'
0(
0*
1+
1,
1-
#630
0,
1.
#640
1#
0$
0%
1(
0+
1,
#650
0,
#660
0#
1&
0'
0(
0)
1*
1+
1,
#670
0,
0-
0.
#680
1%
0&
1)
1,
#690
0,
#700
1$
0%
1(
0+
1,
#710
0,
#720
1%
1'
0(
0*
1+
1,
1-
#730
0,
1.
#740
1#
0$
0%
1(
0+
1,
#750
0,
#760
0#
1&
0'
0(
0)
1*
1+
1,
#770
0,
0-
0.
#780
1%
0&
1)
1,
#790
0,
#800
1$
0%
1(
0+
1,
#810
0,
#820
1%
1'
0(
0*
1+
1,
1-
#830
0,
1.
#840
1#
0$
0%
1(
0+
1,
#850
0,
#860
0#
1&
0'
0(
0)
1*
1+
1,
#870
0,
0-
0.
#880
1%
0&
1)
1,
#890
0,
#900
1$
0%
1(
0+
1,
#910
0,
#920
1%
1'
0(
0*
1+
1,
1-
#930
0,
1.
#940
1#
0$
0%
1(
0+
1,
#950
0,
#960
0#
1&
0'
0(
0)
1*
1+
1,
#970
0,
0-
0.
#980
1%
0&
1)
1,
#990
0,
#1000
1$
0%
1(
0+
1,
#1010
0,
#1020
1%
1'
0(
0*
1+
1,
1-
#1030
0,
1.
#1040
1#
0$
0%
1(
0+
1,
#1050
0,
#1060
0#
1&
0'
0(
0)
1*
1+
1,
#1070
0,
0-
0.
#1080
1%
0&
1)
1,
#1090
0,
#1100
1$
0%
1(
0+
1,
#1110
0,
#1120
1%
1'
0(
0*
1+
1,
1-
#1130
0,
1.
#1140
1#
0$
0%
1(
0+
1,
#1150
0,
#1160
0#
1&
0'
0(
0)
1*
1+
1,
#1170
0,
0-
0.
#1180
1%
0&
1)
1,
#1190
0,
#1200
1$
0%
1(
0+
1,
#1210
0,
#1220
1%
1'
0(
0*
1+
1,
1-
#1230
0,
1.
#1240
1#
0$
0%
1(
0+
1,
#1250
0,
#1260
0#
1&
0'
0(
0)
1*
1+
1,
#1270
0,
0-
0.
#1280
1%
0&
1)
1,
#1290
0,
#1300
1$
0%
1(
0+
1,
#1310
0,
#1320
1%
1'
0(
0*
1+
1,
1-
#1330
0,
1.
#1340
1#
0$
0%
1(
0+
1,
#1350
0,
#1360
0#
1&
0'
0(
0)
1*
1+
1,
#1370
0,
0-
0.
#1380
1%
0&
1)
1,
#1390
0,
#1400
1$
0%
1(
0+
1,
#1410
0,
#1420
1%
1'
0(
0*
1+
1,
1-
#1430
0,
1.
#1440
1#
0$
0%
1(
0+
1,
#1450
0,
#1460
0#
1&
0'
0(
0)
1*
1+
1,
#1470
0,
0-
0.
#1480
1%
0&
1)
1,
#1490
0,
#1500
1$
0%
1(
0+
1,
#1510
0,
#1520
1%
1'
0(
0*
1+
1,
1-
#1530
0,
1.
#1540
1#
0$
0%
1(
0+
1,
#1550
0,
#1560
0#
1&
0'
0(
0)
1*
1+
1,
#1570
0,
0-
0.
#1580
1%
0&
1)
1,
#1590
0,
#1600
1$
0%
1(
0+
1,
#1610
0,
#1620
1%
1'
0(
0*
1+
1,
1-
#1630
0,
1.
#1640
1#
0$
0%
1(
0+
1,
#1650
0,
#1660
0#
1&
0'
0(
0)
1*
1+
1,
#1670
0,
0-
0.
#1680
1%
0&
1)
1,
#1690
0,
#1700
1$
0%
1(
0+
1,
#1710
0,
#1720
1%
1'
0(
0*
1+
1,
1-
#1730
0,
1.
#1740
1#
0$
0%
1(
0+
1,
#1750
0,
#1760
0#
1&
0'
0(
0)
1*
1+
1,
#1770
0,
0-
0.
#1780
1%
0&
1)
1,
#1790
0,
#1800
1$
0%
1(
0+
1,
#1810
0,
#1820
1%
1'
0(
0*
1+
1,
1-
#1830
0,
1.
#1840
1#
0$
0%
1(
0+
1,
#1850
0,
#1860
0#
1&
0'
0(
0)
1*
1+
1,
#1870
0,
0-
0.
#1880
1%
0&
1)
1,
#1890
0,
#1900
1$
0%
1(
0+
1,
#1910
0,
#1920
1%
1'
0(
0*
1+
1,
1-
#1930
0,
1.
#1940
1#
0$
0%
1(
0+
1,
#1950
0,
#1960
0#
1&
0'
0(
0)
1*
1+
1,
#1970
0,
0-
0.
#1980
1%
0&
1)
1,
#1990
0,
#2000
1$
0%
1(
0+
1,
#2010
0,
#2020
1%
1'
0(
0*
1+
1,
1-
#2030
0,
1.
#2040
1#
0$
0%
1(
0+
1,
#2050
0,
#2060
0#
1&
0'
0(
0)
1*
1+
1,
#2070
0,
0-
0.
#2080
1%
0&
1)
1,
#2090
0,
#2100
1$
0%
1(
0+
1,
#2110
0,
#2120
1%
1'
0(
0*
1+
1,
1-
#2130
0,
1.
#2140
1#
0$
0%
1(
0+
1,
#2150
0,
#2160
0#
1&
0'
0(
0)
1*
1+
1,
#2170
0,
0-
0.
#2180
1%
0&
1)
1,
#2190
0,
#2200
1$
0%
1(
0+
1,
#2210
0,
#2220
1%
1'
0(
0*
1+
1,
1-
#2230
0,
1.
#2240
1#
0$
0%
1(
0+
1,
#2250
0,
#2260
0#
1&
0'
0(
0)
1*
1+
1,
#2270
0,
0-
0.
#2280
1%
0&
1)
1,
#2290
0,
#2300
1$
0%
1(
0+
1,
#2310
0,
#2320
1%
1'
0(
0*
1+
1,
1-
#2330
0,
1.
#2340
1#
0$
0%
1(
0+
1,
#2350
0,
#2360
0#
1&
0'
0(
0)
1*
1+
1,
#2370
0,
0-
0.
#2380
1%
0&
1)
1,
#2390
0,
#2400
1$
0%
1(
0+
1,
#2410
0,
#2420
1%
1'
0(
0*
1+
1,
1-
#2430
0,
1.
#2440
1#
0$
0%
1(
0+
1,
#2450
0,
#2460
0#
1&
0'
0(
0)
1*
1+
1,
#2470
0,
0-
0.
#2480
1%
0&
1)
1,
#2490
0,
#2500
1$
0%
1(
0+
1,
#2510
0,
#2520
1%
1'
0(
0*
1+
1,
1-
#2530
0,
1.
#2540
1#
0$
0%
1(
0+
1,
#2550
0,
#2560
0#
1&
0'
0(
0)
1*
1+
1,
#2570
0,
0-
0.
#2580
1%
0&
1)
1,
#2590
0,
#2600
1$
0%
1(
0+
1,
#2610
0,
#2620
1%
1'
0(
0*
1+
1,
1-
#2630
0,
1.
#2640
1#
0$
0%
1(
0+
1,
#2650
0,
#2660
0#
1&
0'
0(
0)
1*
1+
1,
#2670
0,
0-
0.
#2680
1%
0&
1)
1,
#2690
0,
#2700
1$
0%
1(
0+
1,
#2710
0,
#2720
1%
1'
0(
0*
1+
1,
1-
#2730
0,
1.
#2740
1#
0$
0%
1(
0+
1,
#2750
0,
#2760
0#
1&
0'
0(
0)
1*
1+
1,
#2770
0,
0-
0.
#2780
1%
0&
1)
1,
#2790
0,
#2800
1$
0%
1(
0+
1,
#2810
0,
#2820
1%
1'
0(
0*
1+
1,
1-
#2830
0,
1.
#2840
1#
0$
0%
1(
0+
1,
#2850
0,
#2860
0#
1&
0'
0(
0)
1*
1+
1,
#2870
0,
0-
0.
#2880
1%
0&
1)
1,
#2890
0,
#2900
1$
0%
1(
0+
1,
#2910
0,
#2920
1%
1'
0(
0*
1+
1,
1-
#2930
0,
1.
#2940
1#
0$
0%
1(
0+
1,
#2950
0,
#2960
0#
1&
0'
0(
0)
1*
1+
1,
#2970
0,
0-
0.
#2980
1%
0&
1)
1,
#2990
0,
#3000
1$
0%
1(
0+
1,
#3010
0,
#3020
1%
1'
0(
0*
1+
1,
1-
#3030
0,
1.
#3040
1#
0$
0%
1(
0+
1,
#3050
0,
#3060
0#
1&
0'
0(
0)
1*
1+
1,
#3070
0,
0-
0.
#3080
1%
0&
1)
1,
#3090
0,
#3100
1$
0%
1(
0+
1,
#3110
0,
#3120
1%
1'
0(
0*
1+
1,
1-
#3130
0,
1.
#3140
1#
0$
0%
1(
0+
1,
#3150
0,
#3160
0#
1&
0'
0(
0)
1*
1+
1,
#3170
0,
0-
0.
#3180
1%
0&
1)
1,
#3190
0,
#3200
1$
0%
1(
0+
1,
#3210
0,
#3220
1%
1'
0(
0*
1+
1,
1-
#3230
0,
1.
#3240
1#
0$
0%
1(
0+
1,
#3250
0,
#3260
0#
1&
0'
0(
0)
1*
1+
1,
#3270
0,
0-
0.
#3280
1%
0&
1)
1,
#3290
0,
#3300
1$
0%
1(
0+
1,
#3310
0,
#3320
1%
1'
0(
0*
1+
1,
1-
#3330
0,
1.
#3340
1#
0$
0%
1(
0+
1,
#3350
0,
#3360
0#
1&
0'
0(
0)
1*
1+
1,
#3370
0,
0-
0.
#3380
1%
0&
1)
1,
#3390
0,
#3400
1$
0%
1(
0+
1,
#3410
0,
#3420
1%
1'
0(
0*
1+
1,
1-
#3430
0,
1.
#3440
1#
0$
0%
1(
0+
1,
#3450
0,
#3460
0#
1&
0'
0(
0)
1*
1+
1,
#3470
0,
0-
0.
#3480
1%
0&
1)
1,
#3490
0,
#3500
1$
0%
1(
0+
1,
#3510
0,
#3520
1%
1'
0(
0*
1+
1,
1-
#3530
0,
1.
#3540
1#
0$
0%
1(
0+
1,
#3550
0,
#3560
0#
1&
0'
0(
0)
1*
1+
1,
#3570
0,
0-
0.
#3580
1%
0&
1)
1,
#3590
0,
#3600
1$
0%
1(
0+
1,
#3610
0,
#3620
1%
1'
0(
0*
1+
1,
1-
#3630
0,
1.
#3640
1#
0$
0%
1(
0+
1,
#3650
0,
#3660
0#
1&
0'
0(
0)
1*
1+
1,
#3670
0,
0-
0.
#3680
1%
0&
1)
1,
#3690
0,
#3700
1$
0%
1(
0+
1,
#3710
0,
#3720
1%
1'
0(
0*
1+
1,
1-
#3730
0,
1.
#3740
1#
0$
0%
1(
0+
1,
#3750
0,
#3760
0#
1&
0'
0(
0)
1*
1+
1,
#3770
0,
0-
0.
#3780
1%
0&
1)
1,
#3790
0,
#3800
1$
0%
1(
0+
1,
#3810
0,
#3820
1%
1'
0(
0*
1+
1,
1-
#3830
0,
1.
#3840
1#
0$
0%
1(
0+
1,
#3850
0,
#3860
0#
1&
0'
0(
0)
1*
1+
1,
#3870
0,
0-
0.
#3880
1%
0&
1)
1,
#3890
0,
#3900
1$
0%
1(
0+
1,
#3910
0,
#3920
1%
1'
0(
0*
1+
1,
1-
#3930
0,
1.
#3940
1#
0$
0%
1(
0+
1,
#3950
0,
#3960
0#
1&
0'
0(
0)
1*
1+
1,
#3970
0,
0-
0.
#3980
1%
0&
1)
1,
#3990
0,
#4000
1$
0%
1(
0+
1,
#4010
0,
#4020
1%
1'
0(
0*
1+
1,
1-
#4030
0,
1.
#4040
1#
0$
0%
1(
0+
1,
#4050
0,
#4060
0#
1&
0'
0(
0)
1*
1+
1,
#4070
0,
0-
0.
#4080
1%
0&
1)
1,
#4090
0,
#4100
1$
0%
1(
0+
1,
#4110
0,
#4120
1%
1'
0(
0*
1+
1,
1-
#4130
0,
1.
#4140
1#
0$
0%
1(
0+
1,
#4150
0,
#4160
0#
1&
0'
0(
0)
1*
1+
1,
#4170
0,
0-
0.
#4180
1%
0&
1)
1,
#4190
0,
#4200
1$
0%
1(
0+
1,
#4210
0,
#4220
1%
1'
0(
0*
1+
1,
1-
#4230
0,
1.
#4240
1#
0$
0%
1(
0+
1,
#4250
0,
#4260
0#
1&
0'
0(
0)
1*
1+
1,
#4270
0,
0-
0.
#4280
1%
0&
1)
1,
#4290
0,
#4300
1$
0%
1(
0+
1,
#4310
0,
#4320
1%
1'
0(
0*
1+
1,
1-
#4330
0,
1.
#4340
1#
0$
0%
1(
0+
1,
#4350
0,
#4360
0#
1&
0'
0(
0)
1*
1+
1,
#4370
0,
0-
0.
#4380
1%
0&
1)
1,
#4390
0,
#4400
1$
0%
1(
0+
1,
#4410
0,
#4420
1%
1'
0(
0*
1+
1,
1-
#4430
0,
1.
#4440
1#
0$
0%
1(
0+
1,
#4450
0,
#4460
0#
1&
0'
0(
0)
1*
1+
1,
#4470
0,
0-
0.
#4480
1%
0&
1)
1,
#4490
0,
#4500
1$
0%
1(
0+
1,
#4510
0,
#4520
1%
1'
0(
0*
1+
1,
1-
#4530
0,
1.
#4540
1#
0$
0%
1(
0+
1,
#4550
0,
#4560
0#
1&
0'
0(
0)
1*
1+
1,
#4570
0,
0-
0.
#4580
1%
0&
1)
1,
#4590
0,
#4600
1$
0%
1(
0+
1,
#4610
0,
#4620
1%
1'
0(
0*
1+
1,
1-
#4630
0,
1.
#4640
1#
0$
0%
1(
0+
1,
#4650
0,
#4660
0#
1&
0'
0(
0)
1*
1+
1,
#4670
0,
0-
0.
#4680
1%
0&
1)
1,
#4690
0,
#4700
1$
0%
1(
0+
1,
#4710
0,
#4720
1%
1'
0(
0*
1+
1,
1-
#4730
0,
1.
#4740
1#
0$
0%
1(
0+
1,
#4750
0,
#4760
0#
1&
0'
0(
0)
1*
1+
1,
#4770
0,
0-
0.
#4780
1%
0&
1)
1,
#4790
0,
#4800
1$
0%
1(
0+
1,
#4810
0,
#4820
1%
1'
0(
0*
1+
1,
1-
#4830
0,
1.
#4840
1#
0$
0%
1(
0+
1,
#4850
0,
#4860
0#
1&
0'
0(
0)
1*
1+
1,
#4870
0,
0-
0.
#4880
1%
0&
1)
1,
#4890
0,
#4900
1$
0%
1(
0+
1,
#4910
0,
#4920
1%
1'
0(
0*
1+
1,
1-
#4930
0,
1.
#4940
1#
0$
0%
1(
0+
1,
#4950
0,
#4960
0#
1&
0'
0(
0)
1*
1+
1,
#4970
0,
0-
0.
#4980
1%
0&
1)
1,
