round_robin/rrobin.sv
module rrobin(
        input clk,
        input rst_n,
        input req0,
        input req1,
        input req2,
        input req3,
        input ack,
        output logic [1:0] gnt
  );

    logic [1:0] last_grant;
    logic change_state;
    enum logic [1:0] {
        IDLE=2'b00,
        GNTSTATE = 2'b01,
        WAIT = 2'b10
    } state, next_state;

    assign change_state = |{req0, req1, req2, req3};
    always_comb begin
        case(state)
          IDLE: begin
            //gnt = 2'b00;
            //gnt = 2'b00;
            if (change_state) begin
              next_state = GNTSTATE;
            end else begin
              next_state = IDLE;
            end //else
          end //IDLE
          GNTSTATE: begin
              if(last_grant == 2'b00) begin
                if (req1) begin
                  gnt = 2'b01;
                end else if(req2) begin
                  gnt = 2'b10;
                end else if(req3) begin
                  gnt = 2'b11;
                end else if(req0) begin
                  gnt = 2'b00;
                end
              end //last_grant
              else if(last_grant == 2'b01) begin
                if (req2) begin
                  gnt = 2'b10;
                end else if(req3) begin
                  gnt = 2'b11;
                end else if(req0) begin
                  gnt = 2'b00;
                end else if (req1) begin
                  gnt = 2'b01;
                end
              end //last_grant
              else if(last_grant == 2'b10) begin
                if (req3) begin
                  gnt = 2'b11;
                end else if(req0) begin
                  gnt = 2'b00;
                end else if(req1) begin
                  gnt = 2'b01;
                end else if (req2) begin
                  gnt = 2'b10;
                end
              end //last_grant
              else if(last_grant == 2'b11) begin
                if (req0) begin
                  gnt = 2'b00;
                end else if(req1) begin
                  gnt = 2'b01;
                end else if(req2) begin
                  gnt = 2'b10;
                end else if (req3) begin
                  gnt = 2'b11;
                end
              end //last_grant
              next_state = WAIT;
          end //STATE1
          WAIT: begin
            //wait for ack signal and then go to IDLE
            if (ack) begin
              next_state =IDLE;
            end else begin
              next_state = WAIT;
            end
          end
          default: begin
            next_state = IDLE;
          end
      endcase
    end //always_comb
    always_ff @(posedge clk or negedge rst_n) begin
      if(!rst_n) begin
        last_grant <= 2'b00;
        state <= IDLE;
      end else begin
        state <= next_state;
        last_grant <= gnt;;
      end
    end
endmodule

round_robin/trace.vcd
$version Generated by VerilatedVcd $end
$date Mon Jul 25 14:11:50 2022
 $end
$timescale   1ps $end

 $scope module TOP $end
  $var wire  1 ) ack $end
  $var wire  1 # clk $end
  $var wire  2 * gnt [1:0] $end
  $var wire  1 % req0 $end
  $var wire  1 & req1 $end
  $var wire  1 ' req2 $end
  $var wire  1 ( req3 $end
  $var wire  1 $ rst_n $end
  $scope module rrobin $end
   $var wire  1 ) ack $end
   $var wire  1 , change_state $end
   $var wire  1 # clk $end
   $var wire  2 * gnt [1:0] $end
   $var wire  2 + last_grant [1:0] $end
   $var wire  2 . next_state [1:0] $end
   $var wire  1 % req0 $end
   $var wire  1 & req1 $end
   $var wire  1 ' req2 $end
   $var wire  1 ( req3 $end
   $var wire  1 $ rst_n $end
   $var wire  2 - state [1:0] $end
  $upscope $end
 $upscope $end
$enddefinitions $end


#16
0#
1$
1%
0&
0'
0(
0)
b00 *
b00 +
1,
b00 -
b01 .
#26
1#
#36
0#
b01 -
b10 .
#46
1#
#56
0#
b10 -
#66
1#
#76
0#
#86
1#
#102
0#
0%
1)
0,
b00 .
#112
1#
#128
0#
1'
0)
1,
b00 -
b01 .
#138
1#
#148
0#
b10 *
b01 -
b10 .
#158
1#
#168
0#
b10 +
b10 -
#178
1#
#188
0#
#198
1#
#214
0#
0'
1)
0,
b00 .
#224
1#
#240
0#
0)
b00 -
