gray2binary/bin2gray.sv
module bin2gray #(parameter SIZE = 4)
( input [SIZE-1:0] bin,
input clk,
input rst,
input inc,
output reg [SIZE-1:0] gray);

wire [SIZE-1:0] gnext;
wire [SIZE-1:0] bnext;
always @(posedge clk or negedge rst) begin
  if(!rst)
    gray <= {SIZE{1'b0}};
  else
    gray <= gnext;
end
/*
  //gray to binary code
  genvar i;
  always@(*) begin
    for(i=0;i<SIZE;i = i+1)
      bin[i] = ^(gnext >> i);
  end
  */
  /* verilator lint_off WIDTH */
  assign bnext = bin + inc;
  /* verilator lint_on WIDTH */
  assign gnext = (bnext >> 1) ^ bnext;
endmodule

gray2binary/trace.vcd
$version Generated by VerilatedVcd $end
$date Mon Sep 19 09:53:11 2022
 $end
$timescale   1ns $end

 $scope module TOP $end
  $var wire  4 # bin [3:0] $end
  $var wire  1 $ clk $end
  $var wire  4 ' gray [3:0] $end
  $var wire  1 & inc $end
  $var wire  1 % rst $end
  $scope module bin2gray $end
   $var wire 32 * SIZE [31:0] $end
   $var wire  4 # bin [3:0] $end
   $var wire  4 ) bnext [3:0] $end
   $var wire  1 $ clk $end
   $var wire  4 ( gnext [3:0] $end
   $var wire  4 ' gray [3:0] $end
   $var wire  1 & inc $end
   $var wire  1 % rst $end
  $upscope $end
 $upscope $end
$enddefinitions $end


#0
b0000 #
1$
1%
0&
b0000 '
b0000 (
b0000 )
b00000000000000000000000000000100 *
#10
#20
#30
0$
#40
b0001 #
b0001 '
b0001 (
b0001 )
#50
#60
1$
#70
b0010 #
b0011 '
b0011 (
b0010 )
#80
#90
0$
#100
b0011 #
b0010 '
b0010 (
b0011 )
#110
#120
1$
#130
b0100 #
b0110 '
b0110 (
b0100 )
#140
#150
0$
#160
b0101 #
b0111 '
b0111 (
b0101 )
#170
#180
1$
#190
b0110 #
b0101 '
b0101 (
b0110 )
#200
#210
0$
#220
b0111 #
b0100 '
b0100 (
b0111 )
#230
#240
1$
#250
b1000 #
b1100 '
b1100 (
b1000 )
#260
#270
0$
#280
b1001 #
b1101 '
b1101 (
b1001 )
#290
#300
1$
#310
b1010 #
b1111 '
b1111 (
b1010 )
#320
#330
0$
#340
b1011 #
b1110 '
b1110 (
b1011 )
#350
#360
1$
#370
b1100 #
b1010 '
b1010 (
b1100 )
#380
#390
0$
#400
b1101 #
b1011 '
b1011 (
b1101 )
#410
#420
1$
#430
b1110 #
b1001 '
b1001 (
b1110 )
#440
#450
0$
#460
b1111 #
b1000 '
b1000 (
b1111 )
#470
#480
1$
#490
b0000 #
b0000 '
b0000 (
b0000 )
#500
#510
0$
#520
b0001 #
b0001 '
b0001 (
b0001 )
#530
#540
1$
#550
b0010 #
b0011 '
b0011 (
b0010 )
#560
#570
0$
#580
b0011 #
b0010 '
b0010 (
b0011 )
#590
#600
1$
#610
b0100 #
b0110 '
b0110 (
b0100 )
#620
#630
0$
#640
b0101 #
b0111 '
b0111 (
b0101 )
#650
#660
1$
#670
b0110 #
b0101 '
b0101 (
b0110 )
#680
#690
0$
#700
b0111 #
b0100 '
b0100 (
b0111 )
#710
#720
1$
#730
b1000 #
b1100 '
b1100 (
b1000 )
#740
#750
0$
#760
b1001 #
b1101 '
b1101 (
b1001 )
#770
#780
1$
#790
b1010 #
b1111 '
b1111 (
b1010 )
#800
#810
0$
#820
b1011 #
b1110 '
b1110 (
b1011 )
#830
#840
1$
#850
b1100 #
b1010 '
b1010 (
b1100 )
#860
#870
0$
#880
b1101 #
b1011 '
b1011 (
b1101 )
#890
#900
1$
#910
b1110 #
b1001 '
b1001 (
b1110 )
#920
#930
0$
#940
b1111 #
b1000 '
b1000 (
b1111 )
#950
#960
1$
#970
b0000 #
b0000 '
b0000 (
b0000 )
#980
#990
0$
#1000
b0001 #
b0001 '
b0001 (
b0001 )
#1010
#1020
1$
#1030
b0010 #
b0011 '
b0011 (
b0010 )
#1040
#1050
0$
#1060
b0011 #
b0010 '
b0010 (
b0011 )
#1070
#1080
1$
#1090
b0100 #
b0110 '
b0110 (
b0100 )
#1100
#1110
0$
#1120
b0101 #
b0111 '
b0111 (
b0101 )
#1130
#1140
1$
#1150
b0110 #
b0101 '
b0101 (
b0110 )
#1160
#1170
0$
#1180
b0111 #
b0100 '
b0100 (
b0111 )
#1190
#1200
1$
#1210
b1000 #
b1100 '
b1100 (
b1000 )
#1220
#1230
0$
#1240
b1001 #
b1101 '
b1101 (
b1001 )
#1250
#1260
1$
#1270
b1010 #
b1111 '
b1111 (
b1010 )
#1280
#1290
0$
#1300
b1011 #
b1110 '
b1110 (
b1011 )
#1310
#1320
1$
#1330
b1100 #
b1010 '
b1010 (
b1100 )
#1340
#1350
0$
#1360
b1101 #
b1011 '
b1011 (
b1101 )
#1370
#1380
1$
#1390
b1110 #
b1001 '
b1001 (
b1110 )
#1400
#1410
0$
#1420
b1111 #
b1000 '
b1000 (
b1111 )
#1430
#1440
1$
#1450
b0000 #
b0000 '
b0000 (
b0000 )
#1460
#1470
0$
#1480
b0001 #
b0001 '
b0001 (
b0001 )
#1490
#1500
1$
#1510
b0010 #
b0011 '
b0011 (
b0010 )
#1520
#1530
0$
#1540
b0011 #
b0010 '
b0010 (
b0011 )
#1550
#1560
1$
#1570
b0100 #
b0110 '
b0110 (
b0100 )
#1580
#1590
0$
#1600
b0101 #
b0111 '
b0111 (
b0101 )
#1610
#1620
1$
#1630
b0110 #
b0101 '
b0101 (
b0110 )
#1640
#1650
0$
#1660
b0111 #
b0100 '
b0100 (
b0111 )
#1670
#1680
1$
#1690
b1000 #
b1100 '
b1100 (
b1000 )
#1700
#1710
0$
#1720
b1001 #
b1101 '
b1101 (
b1001 )
#1730
#1740
1$
#1750
b1010 #
b1111 '
b1111 (
b1010 )
#1760
#1770
0$
#1780
b1011 #
b1110 '
b1110 (
b1011 )
#1790
#1800
1$
#1810
b1100 #
b1010 '
b1010 (
b1100 )
#1820
#1830
0$
#1840
b1101 #
b1011 '
b1011 (
b1101 )
#1850
#1860
1$
#1870
b1110 #
b1001 '
b1001 (
b1110 )
#1880
#1890
0$
#1900
b1111 #
b1000 '
b1000 (
b1111 )
#1910
#1920
1$
#1930
b0000 #
b0000 '
b0000 (
b0000 )
#1940
#1950
0$
#1960
b0001 #
b0001 '
b0001 (
b0001 )
#1970
#1980
1$
#1990
b0010 #
b0011 '
b0011 (
b0010 )
#2000
#2010
0$
#2020
b0011 #
b0010 '
b0010 (
b0011 )
#2030
#2040
1$
#2050
b0100 #
b0110 '
b0110 (
b0100 )
#2060
#2070
0$
#2080
b0101 #
b0111 '
b0111 (
b0101 )
#2090
#2100
1$
#2110
b0110 #
b0101 '
b0101 (
b0110 )
#2120
#2130
0$
#2140
b0111 #
b0100 '
b0100 (
b0111 )
#2150
#2160
1$
#2170
b1000 #
b1100 '
b1100 (
b1000 )
#2180
#2190
0$
#2200
b1001 #
b1101 '
b1101 (
b1001 )
#2210
#2220
1$
#2230
b1010 #
b1111 '
b1111 (
b1010 )
#2240
#2250
0$
#2260
b1011 #
b1110 '
b1110 (
b1011 )
#2270
#2280
1$
#2290
b1100 #
b1010 '
b1010 (
b1100 )
#2300
#2310
0$
#2320
b1101 #
b1011 '
b1011 (
b1101 )
#2330
#2340
1$
#2350
b1110 #
b1001 '
b1001 (
b1110 )
#2360
#2370
0$
#2380
b1111 #
b1000 '
b1000 (
b1111 )
#2390
#2400
1$
#2410
b0000 #
b0000 '
b0000 (
b0000 )
#2420
#2430
0$
#2440
b0001 #
b0001 '
b0001 (
b0001 )
#2450
#2460
1$
#2470
b0010 #
b0011 '
b0011 (
b0010 )
#2480
#2490
0$
#2500
b0011 #
b0010 '
b0010 (
b0011 )
#2510
#2520
1$
#2530
b0100 #
b0110 '
b0110 (
b0100 )
#2540
#2550
0$
#2560
b0101 #
b0111 '
b0111 (
b0101 )
#2570
#2580
1$
#2590
b0110 #
b0101 '
b0101 (
b0110 )
#2600
#2610
0$
#2620
b0111 #
b0100 '
b0100 (
b0111 )
#2630
#2640
1$
#2650
b1000 #
b1100 '
b1100 (
b1000 )
#2660
#2670
0$
#2680
b1001 #
b1101 '
b1101 (
b1001 )
#2690
#2700
1$
#2710
b1010 #
b1111 '
b1111 (
b1010 )
#2720
#2730
0$
#2740
b1011 #
b1110 '
b1110 (
b1011 )
#2750
#2760
1$
#2770
b1100 #
b1010 '
b1010 (
b1100 )
#2780
#2790
0$
#2800
b1101 #
b1011 '
b1011 (
b1101 )
#2810
#2820
1$
#2830
b1110 #
b1001 '
b1001 (
b1110 )
#2840
#2850
0$
#2860
b1111 #
b1000 '
b1000 (
b1111 )
#2870
#2880
1$
#2890
b0000 #
b0000 '
b0000 (
b0000 )
#2900
#2910
0$
#2920
b0001 #
b0001 '
b0001 (
b0001 )
#2930
#2940
1$
#2950
b0010 #
b0011 '
b0011 (
b0010 )
#2960
#2970
0$
#2980
b0011 #
b0010 '
b0010 (
b0011 )
#2990
#3000
1$
#3010
b0100 #
b0110 '
b0110 (
b0100 )
#3020
#3030
0$
#3040
b0101 #
b0111 '
b0111 (
b0101 )
#3050
#3060
1$
#3070
b0110 #
b0101 '
b0101 (
b0110 )
#3080
#3090
0$
#3100
b0111 #
b0100 '
b0100 (
b0111 )
#3110
#3120
1$
#3130
b1000 #
b1100 '
b1100 (
b1000 )
#3140
#3150
0$
#3160
b1001 #
b1101 '
b1101 (
b1001 )
#3170
#3180
1$
#3190
b1010 #
b1111 '
b1111 (
b1010 )
#3200
#3210
0$
#3220
b1011 #
b1110 '
b1110 (
b1011 )
#3230
#3240
1$
#3250
b1100 #
b1010 '
b1010 (
b1100 )
#3260
#3270
0$
#3280
b1101 #
b1011 '
b1011 (
b1101 )
#3290
#3300
1$
#3310
b1110 #
b1001 '
b1001 (
b1110 )
#3320
#3330
0$
#3340
b1111 #
b1000 '
b1000 (
b1111 )
#3350
#3360
1$
#3370
b0000 #
b0000 '
b0000 (
b0000 )
#3380
#3390
0$
#3400
b0001 #
b0001 '
b0001 (
b0001 )
#3410
#3420
1$
#3430
b0010 #
b0011 '
b0011 (
b0010 )
#3440
#3450
0$
#3460
b0011 #
b0010 '
b0010 (
b0011 )
#3470
#3480
1$
#3490
b0100 #
b0110 '
b0110 (
b0100 )
#3500
#3510
0$
#3520
b0101 #
b0111 '
b0111 (
b0101 )
#3530
#3540
1$
#3550
b0110 #
b0101 '
b0101 (
b0110 )
#3560
#3570
0$
#3580
b0111 #
b0100 '
b0100 (
b0111 )
#3590
#3600
1$
#3610
b1000 #
b1100 '
b1100 (
b1000 )
#3620
#3630
0$
#3640
b1001 #
b1101 '
b1101 (
b1001 )
#3650
#3660
1$
#3670
b1010 #
b1111 '
b1111 (
b1010 )
#3680
#3690
0$
#3700
b1011 #
b1110 '
b1110 (
b1011 )
#3710
#3720
1$
#3730
b1100 #
b1010 '
b1010 (
b1100 )
#3740
#3750
0$
#3760
b1101 #
b1011 '
b1011 (
b1101 )
#3770
#3780
1$
#3790
b1110 #
b1001 '
b1001 (
b1110 )
#3800
#3810
0$
#3820
b1111 #
b1000 '
b1000 (
b1111 )
#3830
#3840
1$
#3850
b0000 #
b0000 '
b0000 (
b0000 )
#3860
#3870
0$
#3880
b0001 #
b0001 '
b0001 (
b0001 )
#3890
#3900
1$
#3910
b0010 #
b0011 '
b0011 (
b0010 )
#3920
#3930
0$
#3940
b0011 #
b0010 '
b0010 (
b0011 )
#3950
#3960
1$
#3970
b0100 #
b0110 '
b0110 (
b0100 )
#3980
#3990
0$
#4000
b0101 #
b0111 '
b0111 (
b0101 )
#4010
#4020
1$
#4030
b0110 #
b0101 '
b0101 (
b0110 )
#4040
#4050
0$
#4060
b0111 #
b0100 '
b0100 (
b0111 )
#4070
#4080
1$
#4090
b1000 #
b1100 '
b1100 (
b1000 )
#4100
#4110
0$
#4120
b1001 #
b1101 '
b1101 (
b1001 )
#4130
#4140
1$
#4150
b1010 #
b1111 '
b1111 (
b1010 )
#4160
#4170
0$
#4180
b1011 #
b1110 '
b1110 (
b1011 )
#4190
#4200
1$
#4210
b1100 #
b1010 '
b1010 (
b1100 )
#4220
#4230
0$
#4240
b1101 #
b1011 '
b1011 (
b1101 )
#4250
#4260
1$
#4270
b1110 #
b1001 '
b1001 (
b1110 )
#4280
#4290
0$
#4300
b1111 #
b1000 '
b1000 (
b1111 )
#4310
#4320
1$
#4330
b0000 #
b0000 '
b0000 (
b0000 )
#4340
#4350
0$
#4360
b0001 #
b0001 '
b0001 (
b0001 )
#4370
#4380
1$
#4390
b0010 #
b0011 '
b0011 (
b0010 )
#4400
#4410
0$
#4420
b0011 #
b0010 '
b0010 (
b0011 )
#4430
#4440
1$
#4450
b0100 #
b0110 '
b0110 (
b0100 )
#4460
#4470
0$
#4480
b0101 #
b0111 '
b0111 (
b0101 )
#4490
#4500
1$
#4510
b0110 #
b0101 '
b0101 (
b0110 )
#4520
#4530
0$
#4540
b0111 #
b0100 '
b0100 (
b0111 )
#4550
#4560
1$
#4570
b1000 #
b1100 '
b1100 (
b1000 )
#4580
#4590
0$
#4600
b1001 #
b1101 '
b1101 (
b1001 )
#4610
#4620
1$
#4630
b1010 #
b1111 '
b1111 (
b1010 )
#4640
#4650
0$
#4660
b1011 #
b1110 '
b1110 (
b1011 )
#4670
#4680
1$
#4690
b1100 #
b1010 '
b1010 (
b1100 )
#4700
#4710
0$
#4720
b1101 #
b1011 '
b1011 (
b1101 )
#4730
#4740
1$
#4750
b1110 #
b1001 '
b1001 (
b1110 )
#4760
#4770
0$
#4780
b1111 #
b1000 '
b1000 (
b1111 )
#4790
#4800
1$
#4810
b0000 #
b0000 '
b0000 (
b0000 )
#4820
#4830
0$
#4840
b0001 #
b0001 '
b0001 (
b0001 )
#4850
#4860
1$
#4870
b0010 #
b0011 '
b0011 (
b0010 )
#4880
#4890
0$
#4900
b0011 #
b0010 '
b0010 (
b0011 )
#4910
#4920
1$
#4930
b0100 #
b0110 '
b0110 (
b0100 )
#4940
#4950
0$
#4960
b0101 #
b0111 '
b0111 (
b0101 )
#4970
#4980
1$
#4990
b0110 #
b0101 '
b0101 (
b0110 )
