divide_3/divide_3.v
module divide_3(
                input clk,
                output clk_out
                );
    wire d1, d0;
    reg q0, q1, q2;

    initial begin
        //clk_out = 0;
        q0 = 0;
        q1 = 0;
    end
    always @(posedge clk) begin
    	q0 <= d0; 

    end
    
    assign d1 = q0;
    
    not(q1bar, q1);
    not(q0bar, q0);
    and(d0,q1bar,q0bar);
    
    always @(posedge clk) begin
    	q1 <= d1;
    	//clk_out <= cout;
    end
    
    always @(negedge clk) begin
    	q2 <= q1;

    end
    assign clk_out = q2 | q1;
endmodule

divide_3/divide_3_tb.v
module test;

  /* Make a reset that pulses once. */
  reg reset = 0;
  initial begin
     $dumpfile("test.vcd");
     $dumpvars(0,test);

     # 17 reset = 1;
     # 11 reset = 0;
     # 29 reset = 1;
     # 5  reset =0;
     # 513 $finish;
  end

  /* Make a regular pulsing clock. */
  reg clk = 0;
  always #1 clk = !clk;

  wire clk_out;
  divide_3 c1 (.clk(clk), 
               .clk_out(clk_out));

  initial
     $monitor("At time %t, value = %h (%0d)",
              $time, clk_out, clk_out);
endmodule // test

divide_3/test.vcd
$date
	Fri Oct 20 18:58:54 2017
$end
$version
	Icarus Verilog
$end
$timescale
	1s
$end
$scope module test $end
$var wire 1 ! clk_out $end
$var reg 1 " clk $end
$var reg 1 # reset $end
$scope module c1 $end
$var wire 1 " clk $end
$var wire 1 ! clk_out $end
$var wire 1 $ d0 $end
$var wire 1 % d1 $end
$var wire 1 & q0bar $end
$var wire 1 ' q1bar $end
$var reg 1 ( q0 $end
$var reg 1 ) q1 $end
$var reg 1 * q2 $end
$upscope $end
$upscope $end
$enddefinitions $end
#0
$dumpvars
0*
0)
0(
1'
1&
0%
1$
0#
0"
0!
$end
#1
0$
0&
1%
1(
1"
#2
0"
#3
1!
0'
1&
1)
0%
0(
1"
#4
1*
0"
#5
1$
1'
0)
1"
#6
0!
0*
0"
#7
0$
0&
1%
1(
1"
#8
0"
#9
1&
1!
0'
0%
0(
1)
1"
#10
1*
0"
#11
1$
1'
0)
1"
#12
0!
0*
0"
#13
0$
0&
1%
1(
1"
#14
0"
#15
1!
0'
1&
1)
0%
0(
1"
#16
1*
0"
#17
1$
1'
0)
1"
1#
#18
0!
0*
0"
#19
0$
0&
1%
1(
1"
#20
0"
#21
1&
1!
0'
0%
0(
1)
1"
#22
1*
0"
#23
1$
1'
0)
1"
#24
0!
0*
0"
#25
0$
0&
1%
1(
1"
#26
0"
#27
1!
0'
1&
1)
0%
0(
1"
#28
1*
0"
0#
#29
1$
1'
0)
1"
#30
0!
0*
0"
#31
0$
0&
1%
1(
1"
#32
0"
#33
1&
1!
0'
0%
0(
1)
1"
#34
1*
0"
#35
1$
1'
0)
1"
#36
0!
0*
0"
#37
0$
0&
1%
1(
1"
#38
0"
#39
1!
0'
1&
1)
0%
0(
1"
#40
1*
0"
#41
1$
1'
0)
1"
#42
0!
0*
0"
#43
0$
0&
1%
1(
1"
#44
0"
#45
1&
1!
0'
0%
0(
1)
1"
#46
1*
0"
#47
1$
1'
0)
1"
#48
0!
0*
0"
#49
0$
0&
1%
1(
1"
#50
0"
#51
1!
0'
1&
1)
0%
0(
1"
#52
1*
0"
#53
1$
1'
0)
1"
#54
0!
0*
0"
#55
0$
0&
1%
1(
1"
#56
0"
#57
1&
1!
0'
0%
0(
1)
1"
1#
#58
1*
0"
#59
1$
1'
0)
1"
#60
0!
0*
0"
#61
0$
0&
1%
1(
1"
#62
0"
0#
#63
1!
0'
1&
1)
0%
0(
1"
#64
1*
0"
#65
1$
1'
0)
1"
#66
0!
0*
0"
#67
0$
0&
1%
1(
1"
#68
0"
#69
1&
1!
0'
0%
0(
1)
1"
#70
1*
0"
#71
1$
1'
0)
1"
#72
0!
0*
0"
#73
0$
0&
1%
1(
1"
#74
0"
#75
1!
0'
1&
1)
0%
0(
1"
#76
1*
0"
#77
1$
1'
0)
1"
#78
0!
0*
0"
#79
0$
0&
1%
1(
1"
#80
0"
#81
1&
1!
0'
0%
0(
1)
1"
#82
1*
0"
#83
1$
1'
0)
1"
#84
0!
0*
0"
#85
0$
0&
1%
1(
1"
#86
0"
#87
1!
0'
1&
1)
0%
0(
1"
#88
1*
0"
#89
1$
1'
0)
1"
#90
0!
0*
0"
#91
0$
0&
1%
1(
1"
#92
0"
#93
1&
1!
0'
0%
0(
1)
1"
#94
1*
0"
#95
1$
1'
0)
1"
#96
0!
0*
0"
#97
0$
0&
1%
1(
1"
#98
0"
#99
1!
0'
1&
1)
0%
0(
1"
#100
1*
0"
#101
1$
1'
0)
1"
#102
0!
0*
0"
#103
0$
0&
1%
1(
1"
#104
0"
#105
1&
1!
0'
0%
0(
1)
1"
#106
1*
0"
#107
1$
1'
0)
1"
#108
0!
0*
0"
#109
0$
0&
1%
1(
1"
#110
0"
#111
1!
0'
1&
1)
0%
0(
1"
#112
1*
0"
#113
1$
1'
0)
1"
#114
0!
0*
0"
#115
0$
0&
1%
1(
1"
#116
0"
#117
1&
1!
0'
0%
0(
1)
1"
#118
1*
0"
#119
1$
1'
0)
1"
#120
0!
0*
0"
#121
0$
0&
1%
1(
1"
#122
0"
#123
1!
0'
1&
1)
0%
0(
1"
#124
1*
0"
#125
1$
1'
0)
1"
#126
0!
0*
0"
#127
0$
0&
1%
1(
1"
#128
0"
#129
1&
1!
0'
0%
0(
1)
1"
#130
1*
0"
#131
1$
1'
0)
1"
#132
0!
0*
0"
#133
0$
0&
1%
1(
1"
#134
0"
#135
1!
0'
1&
1)
0%
0(
1"
#136
1*
0"
#137
1$
1'
0)
1"
#138
0!
0*
0"
#139
0$
0&
1%
1(
1"
#140
0"
#141
1&
1!
0'
0%
0(
1)
1"
#142
1*
0"
#143
1$
1'
0)
1"
#144
0!
0*
0"
#145
0$
0&
1%
1(
1"
#146
0"
#147
1!
0'
1&
1)
0%
0(
1"
#148
1*
0"
#149
1$
1'
0)
1"
#150
0!
0*
0"
#151
0$
0&
1%
1(
1"
#152
0"
#153
1&
1!
0'
0%
0(
1)
1"
#154
1*
0"
#155
1$
1'
0)
1"
#156
0!
0*
0"
#157
0$
0&
1%
1(
1"
#158
0"
#159
1!
0'
1&
1)
0%
0(
1"
#160
1*
0"
#161
1$
1'
0)
1"
#162
0!
0*
0"
#163
0$
0&
1%
1(
1"
#164
0"
#165
1&
1!
0'
0%
0(
1)
1"
#166
1*
0"
#167
1$
1'
0)
1"
#168
0!
0*
0"
#169
0$
0&
1%
1(
1"
#170
0"
#171
1!
0'
1&
1)
0%
0(
1"
#172
1*
0"
#173
1$
1'
0)
1"
#174
0!
0*
0"
#175
0$
0&
1%
1(
1"
#176
0"
#177
1&
1!
0'
0%
0(
1)
1"
#178
1*
0"
#179
1$
1'
0)
1"
#180
0!
0*
0"
#181
0$
0&
1%
1(
1"
#182
0"
#183
1!
0'
1&
1)
0%
0(
1"
#184
1*
0"
#185
1$
1'
0)
1"
#186
0!
0*
0"
#187
0$
0&
1%
1(
1"
#188
0"
#189
1&
1!
0'
0%
0(
1)
1"
#190
1*
0"
#191
1$
1'
0)
1"
#192
0!
0*
0"
#193
0$
0&
1%
1(
1"
#194
0"
#195
1!
0'
1&
1)
0%
0(
1"
#196
1*
0"
#197
1$
1'
0)
1"
#198
0!
0*
0"
#199
0$
0&
1%
1(
1"
#200
0"
#201
1&
1!
0'
0%
0(
1)
1"
#202
1*
0"
#203
1$
1'
0)
1"
#204
0!
0*
0"
#205
0$
0&
1%
1(
1"
#206
0"
#207
1!
0'
1&
1)
0%
0(
1"
#208
1*
0"
#209
1$
1'
0)
1"
#210
0!
0*
0"
#211
0$
0&
1%
1(
1"
#212
0"
#213
1&
1!
0'
0%
0(
1)
1"
#214
1*
0"
#215
1$
1'
0)
1"
#216
0!
0*
0"
#217
0$
0&
1%
1(
1"
#218
0"
#219
1!
0'
1&
1)
0%
0(
1"
#220
1*
0"
#221
1$
1'
0)
1"
#222
0!
0*
0"
#223
0$
0&
1%
1(
1"
#224
0"
#225
1&
1!
0'
0%
0(
1)
1"
#226
1*
0"
#227
1$
1'
0)
1"
#228
0!
0*
0"
#229
0$
0&
1%
1(
1"
#230
0"
#231
1!
0'
1&
1)
0%
0(
1"
#232
1*
0"
#233
1$
1'
0)
1"
#234
0!
0*
0"
#235
0$
0&
1%
1(
1"
#236
0"
#237
1&
1!
0'
0%
0(
1)
1"
#238
1*
0"
#239
1$
1'
0)
1"
#240
0!
0*
0"
#241
0$
0&
1%
1(
1"
#242
0"
#243
1!
0'
1&
1)
0%
0(
1"
#244
1*
0"
#245
1$
1'
0)
1"
#246
0!
0*
0"
#247
0$
0&
1%
1(
1"
#248
0"
#249
1&
1!
0'
0%
0(
1)
1"
#250
1*
0"
#251
1$
1'
0)
1"
#252
0!
0*
0"
#253
0$
0&
1%
1(
1"
#254
0"
#255
1!
0'
1&
1)
0%
0(
1"
#256
1*
0"
#257
1$
1'
0)
1"
#258
0!
0*
0"
#259
0$
0&
1%
1(
1"
#260
0"
#261
1&
1!
0'
0%
0(
1)
1"
#262
1*
0"
#263
1$
1'
0)
1"
#264
0!
0*
0"
#265
0$
0&
1%
1(
1"
#266
0"
#267
1!
0'
1&
1)
0%
0(
1"
#268
1*
0"
#269
1$
1'
0)
1"
#270
0!
0*
0"
#271
0$
0&
1%
1(
1"
#272
0"
#273
1&
1!
0'
0%
0(
1)
1"
#274
1*
0"
#275
1$
1'
0)
1"
#276
0!
0*
0"
#277
0$
0&
1%
1(
1"
#278
0"
#279
1!
0'
1&
1)
0%
0(
1"
#280
1*
0"
#281
1$
1'
0)
1"
#282
0!
0*
0"
#283
0$
0&
1%
1(
1"
#284
0"
#285
1&
1!
0'
0%
0(
1)
1"
#286
1*
0"
#287
1$
1'
0)
1"
#288
0!
0*
0"
#289
0$
0&
1%
1(
1"
#290
0"
#291
1!
0'
1&
1)
0%
0(
1"
#292
1*
0"
#293
1$
1'
0)
1"
#294
0!
0*
0"
#295
0$
0&
1%
1(
1"
#296
0"
#297
1&
1!
0'
0%
0(
1)
1"
#298
1*
0"
#299
1$
1'
0)
1"
#300
0!
0*
0"
#301
0$
0&
1%
1(
1"
#302
0"
#303
1!
0'
1&
1)
0%
0(
1"
#304
1*
0"
#305
1$
1'
0)
1"
#306
0!
0*
0"
#307
0$
0&
1%
1(
1"
#308
0"
#309
1&
1!
0'
0%
0(
1)
1"
#310
1*
0"
#311
1$
1'
0)
1"
#312
0!
0*
0"
#313
0$
0&
1%
1(
1"
#314
0"
#315
1!
0'
1&
1)
0%
0(
1"
#316
1*
0"
#317
1$
1'
0)
1"
#318
0!
0*
0"
#319
0$
0&
1%
1(
1"
#320
0"
#321
1&
1!
0'
0%
0(
1)
1"
#322
1*
0"
#323
1$
1'
0)
1"
#324
0!
0*
0"
#325
0$
0&
1%
1(
1"
#326
0"
#327
1!
0'
1&
1)
0%
0(
1"
#328
1*
0"
#329
1$
1'
0)
1"
#330
0!
0*
0"
#331
0$
0&
1%
1(
1"
#332
0"
#333
1&
1!
0'
0%
0(
1)
1"
#334
1*
0"
#335
1$
1'
0)
1"
#336
0!
0*
0"
#337
0$
0&
1%
1(
1"
#338
0"
#339
1!
0'
1&
1)
0%
0(
1"
#340
1*
0"
#341
1$
1'
0)
1"
#342
0!
0*
0"
#343
0$
0&
1%
1(
1"
#344
0"
#345
1&
1!
0'
0%
0(
1)
1"
#346
1*
0"
#347
1$
1'
0)
1"
#348
0!
0*
0"
#349
0$
0&
1%
1(
1"
#350
0"
#351
1!
0'
1&
1)
0%
0(
1"
#352
1*
0"
#353
1$
1'
0)
1"
#354
0!
0*
0"
#355
0$
0&
1%
1(
1"
#356
0"
#357
1&
1!
0'
0%
0(
1)
1"
#358
1*
0"
#359
1$
1'
0)
1"
#360
0!
0*
0"
#361
0$
0&
1%
1(
1"
#362
0"
#363
1!
0'
1&
1)
0%
0(
1"
#364
1*
0"
#365
1$
1'
0)
1"
#366
0!
0*
0"
#367
0$
0&
1%
1(
1"
#368
0"
#369
1&
1!
0'
0%
0(
1)
1"
#370
1*
0"
#371
1$
1'
0)
1"
#372
0!
0*
0"
#373
0$
0&
1%
1(
1"
#374
0"
#375
1!
0'
1&
1)
0%
0(
1"
#376
1*
0"
#377
1$
1'
0)
1"
#378
0!
0*
0"
#379
0$
0&
1%
1(
1"
#380
0"
#381
1&
1!
0'
0%
0(
1)
1"
#382
1*
0"
#383
1$
1'
0)
1"
#384
0!
0*
0"
#385
0$
0&
1%
1(
1"
#386
0"
#387
1!
0'
1&
1)
0%
0(
1"
#388
1*
0"
#389
1$
1'
0)
1"
#390
0!
0*
0"
#391
0$
0&
1%
1(
1"
#392
0"
#393
1&
1!
0'
0%
0(
1)
1"
#394
1*
0"
#395
1$
1'
0)
1"
#396
0!
0*
0"
#397
0$
0&
1%
1(
1"
#398
0"
#399
1!
0'
1&
1)
0%
0(
1"
#400
1*
0"
#401
1$
1'
0)
1"
#402
0!
0*
0"
#403
0$
0&
1%
1(
1"
#404
0"
#405
1&
1!
0'
0%
0(
1)
1"
#406
1*
0"
#407
1$
1'
0)
1"
#408
0!
0*
0"
#409
0$
0&
1%
1(
1"
#410
0"
#411
1!
0'
1&
1)
0%
0(
1"
#412
1*
0"
#413
1$
1'
0)
1"
#414
0!
0*
0"
#415
0$
0&
1%
1(
1"
#416
0"
#417
1&
1!
0'
0%
0(
1)
1"
#418
1*
0"
#419
1$
1'
0)
1"
#420
0!
0*
0"
#421
0$
0&
1%
1(
1"
#422
0"
#423
1!
0'
1&
1)
0%
0(
1"
#424
1*
0"
#425
1$
1'
0)
1"
#426
0!
0*
0"
#427
0$
0&
1%
1(
1"
#428
0"
#429
1&
1!
0'
0%
0(
1)
1"
#430
1*
0"
#431
1$
1'
0)
1"
#432
0!
0*
0"
#433
0$
0&
1%
1(
1"
#434
0"
#435
1!
0'
1&
1)
0%
0(
1"
#436
1*
0"
#437
1$
1'
0)
1"
#438
0!
0*
0"
#439
0$
0&
1%
1(
1"
#440
0"
#441
1&
1!
0'
0%
0(
1)
1"
#442
1*
0"
#443
1$
1'
0)
1"
#444
0!
0*
0"
#445
0$
0&
1%
1(
1"
#446
0"
#447
1!
0'
1&
1)
0%
0(
1"
#448
1*
0"
#449
1$
1'
0)
1"
#450
0!
0*
0"
#451
0$
0&
1%
1(
1"
#452
0"
#453
1&
1!
0'
0%
0(
1)
1"
#454
1*
0"
#455
1$
1'
0)
1"
#456
0!
0*
0"
#457
0$
0&
1%
1(
1"
#458
0"
#459
1!
0'
1&
1)
0%
0(
1"
#460
1*
0"
#461
1$
1'
0)
1"
#462
0!
0*
0"
#463
0$
0&
1%
1(
1"
#464
0"
#465
1&
1!
0'
0%
0(
1)
1"
#466
1*
0"
#467
1$
1'
0)
1"
#468
0!
0*
0"
#469
0$
0&
1%
1(
1"
#470
0"
#471
1!
0'
1&
1)
0%
0(
1"
#472
1*
0"
#473
1$
1'
0)
1"
#474
0!
0*
0"
#475
0$
0&
1%
1(
1"
#476
0"
#477
1&
1!
0'
0%
0(
1)
1"
#478
1*
0"
#479
1$
1'
0)
1"
#480
0!
0*
0"
#481
0$
0&
1%
1(
1"
#482
0"
#483
1!
0'
1&
1)
0%
0(
1"
#484
1*
0"
#485
1$
1'
0)
1"
#486
0!
0*
0"
#487
0$
0&
1%
1(
1"
#488
0"
#489
1&
1!
0'
0%
0(
1)
1"
#490
1*
0"
#491
1$
1'
0)
1"
#492
0!
0*
0"
#493
0$
0&
1%
1(
1"
#494
0"
#495
1!
0'
1&
1)
0%
0(
1"
#496
1*
0"
#497
1$
1'
0)
1"
#498
0!
0*
0"
#499
0$
0&
1%
1(
1"
#500
0"
#501
1&
1!
0'
0%
0(
1)
1"
#502
1*
0"
#503
1$
1'
0)
1"
#504
0!
0*
0"
#505
0$
0&
1%
1(
1"
#506
0"
#507
1!
0'
1&
1)
0%
0(
1"
#508
1*
0"
#509
1$
1'
0)
1"
#510
0!
0*
0"
#511
0$
0&
1%
1(
1"
#512
0"
#513
1&
1!
0'
0%
0(
1)
1"
#514
1*
0"
#515
1$
1'
0)
1"
#516
0!
0*
0"
#517
0$
0&
1%
1(
1"
#518
0"
#519
1!
0'
1&
1)
0%
0(
1"
#520
1*
0"
#521
1$
1'
0)
1"
#522
0!
0*
0"
#523
0$
0&
1%
1(
1"
#524
0"
#525
1&
1!
0'
0%
0(
1)
1"
#526
1*
0"
#527
1$
1'
0)
1"
#528
0!
0*
0"
#529
0$
0&
1%
1(
1"
#530
0"
#531
1!
0'
1&
1)
0%
0(
1"
#532
1*
0"
#533
1$
1'
0)
1"
#534
0!
0*
0"
#535
0$
0&
1%
1(
1"
#536
0"
#537
1&
1!
0'
0%
0(
1)
1"
#538
1*
0"
#539
1$
1'
0)
1"
#540
0!
0*
0"
#541
0$
0&
1%
1(
1"
#542
0"
#543
1!
0'
1&
1)
0%
0(
1"
#544
1*
0"
#545
1$
1'
0)
1"
#546
0!
0*
0"
#547
0$
0&
1%
1(
1"
#548
0"
#549
1&
1!
0'
0%
0(
1)
1"
#550
1*
0"
#551
1$
1'
0)
1"
#552
0!
0*
0"
#553
0$
0&
1%
1(
1"
#554
0"
#555
1!
0'
1&
1)
0%
0(
1"
#556
1*
0"
#557
1$
1'
0)
1"
#558
0!
0*
0"
#559
0$
0&
1%
1(
1"
#560
0"
#561
1&
1!
0'
0%
0(
1)
1"
#562
1*
0"
#563
1$
1'
0)
1"
#564
0!
0*
0"
#565
0$
0&
1%
1(
1"
#566
0"
#567
1!
0'
1&
1)
0%
0(
1"
#568
1*
0"
#569
1$
1'
0)
1"
#570
0!
0*
0"
#571
0$
0&
1%
1(
1"
#572
0"
#573
1&
1!
0'
0%
0(
1)
1"
#574
1*
0"
#575
1$
1'
0)
1"
